rest_framework_djongo/__init__.py
rest_framework_djongo/fields.py
rest_framework_djongo/generic.py
rest_framework_djongo/models/__init__.py
rest_framework_djongo/models/fields.py
rest_framework_djongo/serializers.py
rest_framework_djongo-0.1.7.dist-info/METADATA
rest_framework_djongo-0.1.7.dist-info/WHEEL
rest_framework_djongo-0.1.7.dist-info/RECORD
