Metadata-Version: 2.3
Name: rest-framework-djongo
Version: 0.1.7
Summary: It is used django + mongodb + djongo + djangorestframework
Keywords: django,djongo,mongodb,pymongo,restframework,rest-framework-djongo
Author: vfeng
Author-email: 1914007838@qq.com
Requires-Python: >=3.9
Classifier: Programming Language :: Python :: 3
Classifier: Programming Language :: Python :: 3.9
Classifier: Programming Language :: Python :: 3.10
Classifier: Programming Language :: Python :: 3.11
Classifier: Programming Language :: Python :: 3.12
Classifier: Programming Language :: Python :: 3.13
Requires-Dist: djongo (>=1.3.7)
Project-URL: Homepage, https://github.com/GodWord/rest_framework_djongo
